shadowsocks/__init__.py
shadowsocks/api/__init__.py
shadowsocks/api/tyz.py
shadowsocks/cipherman.py
shadowsocks/ciphers.py
shadowsocks/consts.py
shadowsocks/core.py
shadowsocks/mdb/__init__.py
shadowsocks/mdb/models.py
shadowsocks/protocol_flag.py
shadowsocks/proxyman.py
shadowsocks/server.py
shadowsocks/utils.py
shadowsocks_async-0.1.0.dist-info/entry_points.txt
shadowsocks_async-0.1.0.dist-info/LICENSE
shadowsocks_async-0.1.0.dist-info/WHEEL
shadowsocks_async-0.1.0.dist-info/METADATA
shadowsocks_async-0.1.0.dist-info/RECORD
